README.txt
setup.py
collective/__init__.py
collective.directoryresourcepatch.egg-info/PKG-INFO
collective.directoryresourcepatch.egg-info/SOURCES.txt
collective.directoryresourcepatch.egg-info/dependency_links.txt
collective.directoryresourcepatch.egg-info/entry_points.txt
collective.directoryresourcepatch.egg-info/namespace_packages.txt
collective.directoryresourcepatch.egg-info/not-zip-safe
collective.directoryresourcepatch.egg-info/requires.txt
collective.directoryresourcepatch.egg-info/top_level.txt
collective/directoryresourcepatch/__init__.py
collective/directoryresourcepatch/configure.zcml
collective/directoryresourcepatch/patch.py
docs/HISTORY.txt
docs/INSTALL.txt
docs/LICENSE.GPL
docs/LICENSE.txt