Metadata-Version: 1.0
Name: collective.directoryresourcepatch
Version: 1.1
Summary: Patch for DirectoryResource to allow traversal
Home-page: http://svn.plone.org/svn/collective/collective.directoryresourcepatch/
Author: Michael Dunlap
Author-email: dunlapm@uw.edu
License: GPL
Platform: UNKNOWN
Classifier: Framework :: Plone
Classifier: Programming Language :: Python
